[{"time":"06:46","aircraft":[{"hex":"7c4a53","flight":"JST972  ","lat":-37.651382,"lon":144.668319,"alt_baro":4975,"gs":258,"track":275,"category":"A3"},{"hex":"7c531d","flight":"QFA30   ","lat":-37.305725,"lon":144.768131,"alt_baro":8800,"gs":378,"track":168,"category":"A5"},{"hex":"7c77fa","flight":"QFA151  ","lat":-37.599777,"lon":144.824524,"alt_baro":2800,"gs":200,"track":357,"category":"A0"},{"hex":"7c7aa6","flight":"VOZ807  ","lat":-37.340607,"lon":145.087144,"alt_baro":11950,"gs":335,"track":54,"category":"A0"},{"hex":"7c4a50","flight":"JST34   ","lat":-37.041183,"lon":145.116363,"alt_baro":19625,"gs":378,"track":22,"category":"A3"},{"hex":"7c6dec","flight":"QFA406  ","lat":-37.084956,"lon":145.534695,"alt_baro":26925,"gs":454,"track":54,"category":"A0"}]}]