[{"time":"01:25","aircraft":[{"hex":"7c7cc2","flight":"HM4     ","lat":-38.15859,"lon":143.798855,"alt_baro":1300,"gs":156,"track":79,"category":"A7"},{"hex":"7c4ef4","flight":"POL31   ","lat":-37.900378,"lon":145.044876,"alt_baro":1875,"gs":90,"track":138,"category":null},{"hex":"7cac27","flight":"8AH     ","lat":-37.261203,"lon":145.749107,"alt_baro":9875,"gs":151,"track":234,"category":"A2"}]},{"time":"06:00","aircraft":[{"hex":"7c7891","flight":"JST602  ","lat":-37.802465,"lon":144.701465,"alt_baro":8250,"gs":372,"track":38,"category":"A0"},{"hex":"896523","flight":"UAE1CR  ","lat":-37.692323,"lon":144.842257,"alt_baro":300,"gs":134,"track":352,"category":"A5"},{"hex":"7cad41","flight":"VOZ096  ","lat":-37.574387,"lon":145.007668,"alt_baro":4000,"gs":260,"track":114,"category":"A3"},{"hex":"7c806f","flight":"QFA94   ","lat":-37.465939,"lon":145.611778,"alt_baro":14375,"gs":333,"track":235,"category":"A5"}]}]