[{"time":"02:37","aircraft":[]},{"time":"06:15","aircraft":[{"hex":"7c6d9a","flight":"QFA761  ","lat":-37.596984,"lon":143.84274,"alt_baro":19675,"gs":401,"track":275,"category":"A0"},{"hex":"76cd14","flight":"SIA248  ","lat":-37.402542,"lon":144.455605,"alt_baro":12450,"gs":302,"track":327,"category":"A5"},{"hex":"7c6b07","flight":"JST602  ","lat":-37.985229,"lon":144.501947,"alt_baro":1400,"gs":210,"track":48,"category":"A0"},{"hex":"7c78b3","flight":"QLK1514 ","lat":-37.619797,"lon":144.643951,"alt_baro":5875,"gs":265,"track":341,"category":"A3"},{"hex":"7cad41","flight":"VOZ096  ","lat":-37.814429,"lon":144.732752,"alt_baro":3750,"gs":245,"track":156,"category":"A3"},{"hex":"780abc","flight":"CPA135  ","lat":-37.332001,"lon":144.774735,"alt_baro":8500,"gs":287,"track":169,"category":"A5"},{"hex":"7c6c9b","flight":"JST500  ","lat":-37.608017,"lon":144.826912,"alt_baro":1850,"gs":224,"track":352,"category":"A0"},{"hex":"7c7cc5","flight":"HM3     ","lat":-37.568727,"lon":144.913191,"alt_baro":5475,"gs":130,"track":298,"category":"A7"},{"hex":"7c6de9","flight":"QFA046  ","lat":-37.666901,"lon":144.927433,"alt_baro":1150,"gs":150,"track":274,"category":"A0"}]}]